issurge/__init__.py
issurge/github.py
issurge/interactive.py
issurge/interactive_test.py
issurge/main.py
issurge/main_test.py
issurge/parser.py
issurge/parser_test.py
issurge/utils.py
issurge/utils_test.py
issurge-1.2.1.dist-info/METADATA
issurge-1.2.1.dist-info/WHEEL
issurge-1.2.1.dist-info/entry_points.txt
issurge-1.2.1.dist-info/licenses/LICENSE
issurge-1.2.1.dist-info/RECORD
