Metadata-Version: 2.4
Name: issurge
Version: 1.2.1
Summary: Deal with your client's feedback efficiently by creating a bunch of issues in bulk from a text file.
Project-URL: Repository, https://github.com/gwennlbh/issurge
Author-email: Gwenn Le Bihan <gwenn.lebihan7@gmail.com>
License-File: LICENSE
Classifier: Development Status :: 5 - Production/Stable
Classifier: Programming Language :: Python :: 3
Classifier: Programming Language :: Python :: 3.11
Classifier: Programming Language :: Python :: 3.12
Classifier: Programming Language :: Python :: 3.13
Classifier: Programming Language :: Python :: 3.14
Requires-Python: >=3.10
Requires-Dist: docopt<0.7,>=0.6.2
Requires-Dist: rich<15,>=14.2.0
